keras_flower/__init__.py
keras_flower/util.py
keras_flower-0.3.dist-info/METADATA
keras_flower-0.3.dist-info/WHEEL
keras_flower-0.3.dist-info/top_level.txt
keras_flower-0.3.dist-info/RECORD
