Metadata-Version: 2.1
Name: keras-flower
Version: 0.3
Summary: A Simple Flower classification package trained on DenseNet201
Home-page: https://github.com/Bhanuchander210/keras_flower.git
Author: Bhanuchander Udhayakumar
Author-email: bhanuchander210@gmail.com
License: MIT
Platform: UNKNOWN
Requires-Dist: tensorflow (==2.8.0)
Requires-Dist: keras (==2.8.0)
Requires-Dist: pillow (>=8.0.1)
